hdforce/AuthManager.py
hdforce/Classes.py
hdforce/CreateAthletes.py
hdforce/GetAthletes.py
hdforce/GetForceTime.py
hdforce/GetGroups.py
hdforce/GetMetrics.py
hdforce/GetTags.py
hdforce/GetTeams.py
hdforce/GetTests.py
hdforce/GetTestsAth.py
hdforce/GetTestsGroup.py
hdforce/GetTestsTeam.py
hdforce/GetTestsType.py
hdforce/GetTypes.py
hdforce/LoggerConfig.py
hdforce/UpdateAthletes.py
hdforce/__init__.py
hdforce/data/MetricDictionary.parquet
hdforce/utils.py
hdforce-1.1.3.dist-info/LICENSE.txt
hdforce-1.1.3.dist-info/METADATA
hdforce-1.1.3.dist-info/WHEEL
hdforce-1.1.3.dist-info/RECORD
