Metadata-Version: 2.3
Name: hdforce
Version: 1.1.3
Summary: Get your data from the Hawkin Dynamics API
Keywords: hawkin,force plates,sports science
Author: laureng-hd
Author-email: lauren@hawkindynamics.com
Requires-Python: >=3.9,<4.0
Classifier: Development Status :: 5 - Production/Stable
Classifier: Intended Audience :: Developers
Classifier: License :: OSI Approved :: MIT License
Classifier: Programming Language :: Python :: 3
Classifier: Programming Language :: Python :: 3.9
Classifier: Programming Language :: Python :: 3.10
Classifier: Programming Language :: Python :: 3.11
Classifier: Programming Language :: Python :: 3.12
Classifier: Programming Language :: Python :: 3.13
Classifier: Topic :: Software Development :: Build Tools
Requires-Dist: flake8 (>=7.0.0,<8.0.0)
Requires-Dist: pandas (>=2.2.0,<3.0.0)
Requires-Dist: pyarrow (>=18.1.0,<19.0.0)
Requires-Dist: pydantic (>=2.0.0,<3.0.0)
Requires-Dist: pyjanitor (>=0.30.0,<0.31.0)
Requires-Dist: pytest (>=8.2.0,<9.0.0)
Requires-Dist: python-dotenv (>=1.0.1,<2.0.0)
Requires-Dist: requests (>=2.31.0,<3.0.0)
Project-URL: Documentation, https://hawkindynamics.github.io/hawkinPy/
Project-URL: Homepage, https://www.hawkindynamics.com/
Project-URL: Repository, https://github.com/HawkinDynamics/hawkinPy
